neuralgcm/__init__.py
neuralgcm/demo.py
neuralgcm/data/era5_tl31_19590102T00.nc
neuralgcm/data/tl63_stochastic_mini.pkl
neuralgcm/experimental/__init__.py
neuralgcm/experimental/atmosphere/__init__.py
neuralgcm/experimental/atmosphere/diagnostics.py
neuralgcm/experimental/atmosphere/diagnostics_test.py
neuralgcm/experimental/atmosphere/equations.py
neuralgcm/experimental/atmosphere/observation_operators.py
neuralgcm/experimental/atmosphere/observation_operators_test.py
neuralgcm/experimental/atmosphere/parameterizations.py
neuralgcm/experimental/atmosphere/state_conversion.py
neuralgcm/experimental/atmosphere/transforms.py
neuralgcm/experimental/atmosphere/transforms_test.py
neuralgcm/experimental/core/__init__.py
neuralgcm/experimental/core/api.py
neuralgcm/experimental/core/array_transforms.py
neuralgcm/experimental/core/boundaries.py
neuralgcm/experimental/core/boundaries_test.py
neuralgcm/experimental/core/checkpointing.py
neuralgcm/experimental/core/checkpointing_test.py
neuralgcm/experimental/core/coordinates.py
neuralgcm/experimental/core/coordinates_test.py
neuralgcm/experimental/core/data_specs.py
neuralgcm/experimental/core/diagnostics.py
neuralgcm/experimental/core/diagnostics_test.py
neuralgcm/experimental/core/dynamic_io.py
neuralgcm/experimental/core/equations.py
neuralgcm/experimental/core/feature_transforms.py
neuralgcm/experimental/core/feature_transforms_test.py
neuralgcm/experimental/core/fiddle_tags.py
neuralgcm/experimental/core/field_utils.py
neuralgcm/experimental/core/field_utils_test.py
neuralgcm/experimental/core/interpolators.py
neuralgcm/experimental/core/interpolators_test.py
neuralgcm/experimental/core/learned_transforms.py
neuralgcm/experimental/core/learned_transforms_test.py
neuralgcm/experimental/core/module_utils.py
neuralgcm/experimental/core/nnx_compat.py
neuralgcm/experimental/core/normalizations.py
neuralgcm/experimental/core/normalizations_test.py
neuralgcm/experimental/core/observation_operators.py
neuralgcm-1.2.2.dist-info/licenses/LICENSE
neuralgcm-1.2.2.dist-info/METADATA
neuralgcm-1.2.2.dist-info/WHEEL
neuralgcm-1.2.2.dist-info/top_level.txt
neuralgcm-1.2.2.dist-info/RECORD
